code_library/__init__.py
yamm_library-0.0.1.1.dist-info/METADATA
yamm_library-0.0.1.1.dist-info/WHEEL
yamm_library-0.0.1.1.dist-info/top_level.txt
yamm_library-0.0.1.1.dist-info/RECORD
