Metadata-Version: 2.1
Name: yamm-library
Version: 0.0.1.1
Summary: Pls don't use this.
Home-page: UNKNOWN
Author: Yamm Elnekave
Author-email: elnekave.yamm@gmail.com
License: MIT
Platform: UNKNOWN
Requires-Python: >=3.0
